gradio_pianoroll/__init__.py
gradio_pianoroll/__init__.pyi
gradio_pianoroll/data_models.py
gradio_pianoroll/data_models.pyi
gradio_pianoroll/pianoroll.py
gradio_pianoroll/pianoroll.pyi
gradio_pianoroll/timing_utils.py
gradio_pianoroll/timing_utils.pyi
gradio_pianoroll/templates/component/index.js
gradio_pianoroll/templates/component/style.css
gradio_pianoroll/templates/example/index.js
gradio_pianoroll/templates/example/style.css
gradio_pianoroll/utils/__init__.py
gradio_pianoroll/utils/__init__.pyi
gradio_pianoroll/utils/research.py
gradio_pianoroll/utils/research.pyi
gradio_pianoroll/utils/templates.py
gradio_pianoroll/utils/templates.pyi
gradio_pianoroll-0.0.9.dist-info/METADATA
gradio_pianoroll-0.0.9.dist-info/WHEEL
gradio_pianoroll-0.0.9.dist-info/RECORD
