Metadata-Version: 2.4
Name: gradio_pianoroll
Version: 0.0.9
Summary: A PianoRoll Component for Gradio.
Project-URL: repository, https://github.com/crlotwhite/gradio-pianoroll
Project-URL: space, https://huggingface.co/spaces/crlotwhite/gradio_pianoroll
Author-email: crlotwhite <crlotwhite@gmail.com>
License-Expression: Apache-2.0
Keywords: audio,gradio-custom-component,gradio-template-Fallback
Classifier: Development Status :: 3 - Alpha
Classifier: Operating System :: OS Independent
Classifier: Programming Language :: Python :: 3
Classifier: Programming Language :: Python :: 3 :: Only
Classifier: Programming Language :: Python :: 3.8
Classifier: Programming Language :: Python :: 3.9
Classifier: Programming Language :: Python :: 3.10
Classifier: Programming Language :: Python :: 3.11
Classifier: Topic :: Scientific/Engineering
Classifier: Topic :: Scientific/Engineering :: Artificial Intelligence
Classifier: Topic :: Scientific/Engineering :: Visualization
Requires-Python: >=3.10
Requires-Dist: gradio<6.0,>=4.0
Provides-Extra: dev
Requires-Dist: black>=23.0.0; extra == 'dev'
Requires-Dist: build; extra == 'dev'
Requires-Dist: flake8>=6.0.0; extra == 'dev'
Requires-Dist: isort>=5.12.0; extra == 'dev'
Requires-Dist: mypy>=1.5.0; extra == 'dev'
Requires-Dist: pytest>=7.0.0; extra == 'dev'
Requires-Dist: twine; extra == 'dev'
Provides-Extra: docs
Requires-Dist: mkdocs-include-markdown-plugin>=6.0.0; extra == 'docs'
Requires-Dist: mkdocs-material>=9.0.0; extra == 'docs'
Requires-Dist: mkdocs>=1.5.0; extra == 'docs'
Requires-Dist: pymdown-extensions>=10.0.0; extra == 'docs'
Provides-Extra: quality
Requires-Dist: black>=23.0.0; extra == 'quality'
Requires-Dist: flake8>=6.0.0; extra == 'quality'
Requires-Dist: isort>=5.12.0; extra == 'quality'
Requires-Dist: mypy>=1.5.0; extra == 'quality'
